pybeandi/__init__.py
pybeandi/beans_list.py
pybeandi/config.py
pybeandi/context.py
pybeandi/decorators.py
pybeandi/errors.py
pybeandi/model.py
pybeandi/util.py
pybeandi/test/__init__.py
pybeandi/test/beans_with_inject.py
pybeandi/test/conftest.py
pybeandi/test/test_config.py
pybeandi/test/test_context.py
pybeandi-0.2.4.dist-info/LICENSE
pybeandi-0.2.4.dist-info/METADATA
pybeandi-0.2.4.dist-info/WHEEL
pybeandi-0.2.4.dist-info/top_level.txt
pybeandi-0.2.4.dist-info/RECORD
