Metadata-Version: 2.1
Name: pybeandi
Version: 0.2.4
Summary: Python Dependency Injection library
Home-page: https://gitlab.com/discrimy/pybeandi
Author: Aleksander Bespalov
Author-email: discrimy.off@gmail.com
License: UNKNOWN
Platform: UNKNOWN
Classifier: Programming Language :: Python :: 3
Classifier: License :: OSI Approved :: MIT License
Classifier: Operating System :: OS Independent
Requires-Python: >=3.7
License-File: LICENSE
Requires-Dist: PyYAML (>=5.3.1)
Requires-Dist: mashumaro (~=1.13)
Requires-Dist: loguru (~=0.5.3)
